csa_da_fir/src/csa_da_openlane.v
module csa_da_openlane (
    input  wire        clk,
    input  wire        rst,
    input  wire [7:0]  x,
    output wire [15:0] led
);

    // ---------------- COEFFICIENTS (ROM as localparams) ----------------//
    // Avoids initial-block memory-ROM inference, which is fragile across
    // Yosys versions. A flat case/localparam select synthesizes
    // deterministically as combinational logic on every Yosys build.
    localparam [7:0] H0  = 8'd23,  H1  = 8'd57,  H2  = 8'd91,  H3  = 8'd13,
                      H4  = 8'd77,  H5  = 8'd45,  H6  = 8'd99,  H7  = 8'd31,
                      H8  = 8'd62,  H9  = 8'd88,  H10 = 8'd17,  H11 = 8'd53,
                      H12 = 8'd29,  H13 = 8'd74,  H14 = 8'd66,  H15 = 8'd81;

    // ---------------- SHIFT REGISTER (flattened, no unpacked array) ----//
    // 16 taps x 8 bits, each tap is its own named reg instead of
    // reg [7:0] shift[15:0] -- this keeps Yosys from ever considering
    // memory inference for what is really just a shift register.
    reg [7:0] sh0, sh1, sh2, sh3, sh4, sh5, sh6, sh7;
    reg [7:0] sh8, sh9, sh10, sh11, sh12, sh13, sh14, sh15;

    always @(posedge clk or posedge rst) begin
        if (rst) begin
            sh0  <= 8'd0;  sh1  <= 8'd0;  sh2  <= 8'd0;  sh3  <= 8'd0;
            sh4  <= 8'd0;  sh5  <= 8'd0;  sh6  <= 8'd0;  sh7  <= 8'd0;
            sh8  <= 8'd0;  sh9  <= 8'd0;  sh10 <= 8'd0;  sh11 <= 8'd0;
            sh12 <= 8'd0;  sh13 <= 8'd0;  sh14 <= 8'd0;  sh15 <= 8'd0;
        end else begin
            sh0  <= x;
            sh1  <= sh0;   sh2  <= sh1;   sh3  <= sh2;   sh4  <= sh3;
            sh5  <= sh4;   sh6  <= sh5;   sh7  <= sh6;   sh8  <= sh7;
            sh9  <= sh8;   sh10 <= sh9;   sh11 <= sh10;  sh12 <= sh11;
            sh13 <= sh12;  sh14 <= sh13;  sh15 <= sh14;
        end
    end

    // ---------------- BIT-SLICE DA ----------------//
    // bit_sum[i] = sum of h[k] over all taps where bit i of that tap is 1.
    // Max possible value = sum(all h) = 906 -> fits in 10 bits.
    reg [9:0] bit_sum0, bit_sum1, bit_sum2, bit_sum3;
    reg [9:0] bit_sum4, bit_sum5, bit_sum6, bit_sum7;

    always @(posedge clk or posedge rst) begin
        if (rst) begin
            bit_sum0 <= 10'd0; bit_sum1 <= 10'd0; bit_sum2 <= 10'd0; bit_sum3 <= 10'd0;
            bit_sum4 <= 10'd0; bit_sum5 <= 10'd0; bit_sum6 <= 10'd0; bit_sum7 <= 10'd0;
        end else begin
            bit_sum0 <= (sh0[0]?H0:10'd0)+(sh1[0]?H1:10'd0)+(sh2[0]?H2:10'd0)+(sh3[0]?H3:10'd0)+
                        (sh4[0]?H4:10'd0)+(sh5[0]?H5:10'd0)+(sh6[0]?H6:10'd0)+(sh7[0]?H7:10'd0)+
                        (sh8[0]?H8:10'd0)+(sh9[0]?H9:10'd0)+(sh10[0]?H10:10'd0)+(sh11[0]?H11:10'd0)+
                        (sh12[0]?H12:10'd0)+(sh13[0]?H13:10'd0)+(sh14[0]?H14:10'd0)+(sh15[0]?H15:10'd0);

            bit_sum1 <= (sh0[1]?H0:10'd0)+(sh1[1]?H1:10'd0)+(sh2[1]?H2:10'd0)+(sh3[1]?H3:10'd0)+
                        (sh4[1]?H4:10'd0)+(sh5[1]?H5:10'd0)+(sh6[1]?H6:10'd0)+(sh7[1]?H7:10'd0)+
                        (sh8[1]?H8:10'd0)+(sh9[1]?H9:10'd0)+(sh10[1]?H10:10'd0)+(sh11[1]?H11:10'd0)+
                        (sh12[1]?H12:10'd0)+(sh13[1]?H13:10'd0)+(sh14[1]?H14:10'd0)+(sh15[1]?H15:10'd0);

            bit_sum2 <= (sh0[2]?H0:10'd0)+(sh1[2]?H1:10'd0)+(sh2[2]?H2:10'd0)+(sh3[2]?H3:10'd0)+
                        (sh4[2]?H4:10'd0)+(sh5[2]?H5:10'd0)+(sh6[2]?H6:10'd0)+(sh7[2]?H7:10'd0)+
                        (sh8[2]?H8:10'd0)+(sh9[2]?H9:10'd0)+(sh10[2]?H10:10'd0)+(sh11[2]?H11:10'd0)+
                        (sh12[2]?H12:10'd0)+(sh13[2]?H13:10'd0)+(sh14[2]?H14:10'd0)+(sh15[2]?H15:10'd0);

            bit_sum3 <= (sh0[3]?H0:10'd0)+(sh1[3]?H1:10'd0)+(sh2[3]?H2:10'd0)+(sh3[3]?H3:10'd0)+
                        (sh4[3]?H4:10'd0)+(sh5[3]?H5:10'd0)+(sh6[3]?H6:10'd0)+(sh7[3]?H7:10'd0)+
                        (sh8[3]?H8:10'd0)+(sh9[3]?H9:10'd0)+(sh10[3]?H10:10'd0)+(sh11[3]?H11:10'd0)+
                        (sh12[3]?H12:10'd0)+(sh13[3]?H13:10'd0)+(sh14[3]?H14:10'd0)+(sh15[3]?H15:10'd0);

            bit_sum4 <= (sh0[4]?H0:10'd0)+(sh1[4]?H1:10'd0)+(sh2[4]?H2:10'd0)+(sh3[4]?H3:10'd0)+
                        (sh4[4]?H4:10'd0)+(sh5[4]?H5:10'd0)+(sh6[4]?H6:10'd0)+(sh7[4]?H7:10'd0)+
                        (sh8[4]?H8:10'd0)+(sh9[4]?H9:10'd0)+(sh10[4]?H10:10'd0)+(sh11[4]?H11:10'd0)+
                        (sh12[4]?H12:10'd0)+(sh13[4]?H13:10'd0)+(sh14[4]?H14:10'd0)+(sh15[4]?H15:10'd0);

            bit_sum5 <= (sh0[5]?H0:10'd0)+(sh1[5]?H1:10'd0)+(sh2[5]?H2:10'd0)+(sh3[5]?H3:10'd0)+
                        (sh4[5]?H4:10'd0)+(sh5[5]?H5:10'd0)+(sh6[5]?H6:10'd0)+(sh7[5]?H7:10'd0)+
                        (sh8[5]?H8:10'd0)+(sh9[5]?H9:10'd0)+(sh10[5]?H10:10'd0)+(sh11[5]?H11:10'd0)+
                        (sh12[5]?H12:10'd0)+(sh13[5]?H13:10'd0)+(sh14[5]?H14:10'd0)+(sh15[5]?H15:10'd0);

            bit_sum6 <= (sh0[6]?H0:10'd0)+(sh1[6]?H1:10'd0)+(sh2[6]?H2:10'd0)+(sh3[6]?H3:10'd0)+
                        (sh4[6]?H4:10'd0)+(sh5[6]?H5:10'd0)+(sh6[6]?H6:10'd0)+(sh7[6]?H7:10'd0)+
                        (sh8[6]?H8:10'd0)+(sh9[6]?H9:10'd0)+(sh10[6]?H10:10'd0)+(sh11[6]?H11:10'd0)+
                        (sh12[6]?H12:10'd0)+(sh13[6]?H13:10'd0)+(sh14[6]?H14:10'd0)+(sh15[6]?H15:10'd0);

            bit_sum7 <= (sh0[7]?H0:10'd0)+(sh1[7]?H1:10'd0)+(sh2[7]?H2:10'd0)+(sh3[7]?H3:10'd0)+
                        (sh4[7]?H4:10'd0)+(sh5[7]?H5:10'd0)+(sh6[7]?H6:10'd0)+(sh7[7]?H7:10'd0)+
                        (sh8[7]?H8:10'd0)+(sh9[7]?H9:10'd0)+(sh10[7]?H10:10'd0)+(sh11[7]?H11:10'd0)+
                        (sh12[7]?H12:10'd0)+(sh13[7]?H13:10'd0)+(sh14[7]?H14:10'd0)+(sh15[7]?H15:10'd0);
        end
    end

    // ---------------- SHIFT (bit-weight scaling) ----------------//
    // s[i] = bit_sum[i] << i, max value 906<<7 = 115968 -> fits in 17 bits.
    wire [16:0] bit_sum0_ext = {7'd0, bit_sum0};
    reg  [16:0] s0, s1, s2, s3, s4, s5, s6, s7;

    always @(posedge clk or posedge rst) begin
        if (rst) begin
            s0 <= 17'd0; s1 <= 17'd0; s2 <= 17'd0; s3 <= 17'd0;
            s4 <= 17'd0; s5 <= 17'd0; s6 <= 17'd0; s7 <= 17'd0;
        end else begin
            s0 <= {7'd0, bit_sum0} << 0;
            s1 <= {7'd0, bit_sum1} << 1;
            s2 <= {7'd0, bit_sum2} << 2;
            s3 <= {7'd0, bit_sum3} << 3;
            s4 <= {7'd0, bit_sum4} << 4;
            s5 <= {7'd0, bit_sum5} << 5;
            s6 <= {7'd0, bit_sum6} << 6;
            s7 <= {7'd0, bit_sum7} << 7;
        end
    end

    // ---------------- CSA TREE ----------------//
    // Carries are shifted left by 1 at each merge per standard carry-save
    // convention. Width grows by at most 1 bit per level; 18 bits is
    // sufficient headroom through to final_sum (theoretical max = 231030,
    // which needs 18 bits).
    reg [17:0] sum1, carry1;
    always @(posedge clk or posedge rst) begin
        if (rst) begin
            sum1 <= 18'd0; carry1 <= 18'd0;
        end else begin
            sum1   <= s0 ^ s1 ^ s2;
            carry1 <= (s0 & s1) | (s1 & s2) | (s2 & s0);
        end
    end

    reg [17:0] sum2, carry2;
    always @(posedge clk or posedge rst) begin
        if (rst) begin
            sum2 <= 18'd0; carry2 <= 18'd0;
        end else begin
            sum2   <= sum1 ^ (carry1 << 1) ^ s3;
            carry2 <= (sum1 & (carry1 << 1)) | (s3 & (carry1 << 1)) | (sum1 & s3);
        end
    end

    reg [17:0] sum3, carry3;
    always @(posedge clk or posedge rst) begin
        if (rst) begin
            sum3 <= 18'd0; carry3 <= 18'd0;
        end else begin
            sum3   <= sum2 ^ (carry2 << 1) ^ s4;
            carry3 <= (sum2 & (carry2 << 1)) | (s4 & (carry2 << 1)) | (sum2 & s4);
        end
    end

    reg [17:0] sum4, carry4;
    always @(posedge clk or posedge rst) begin
        if (rst) begin
            sum4 <= 18'd0; carry4 <= 18'd0;
        end else begin
            sum4   <= sum3 ^ (carry3 << 1) ^ s5;
            carry4 <= (sum3 & (carry3 << 1)) | (s5 & (carry3 << 1)) | (sum3 & s5);
        end
    end

    reg [17:0] sum5, carry5;
    always @(posedge clk or posedge rst) begin
        if (rst) begin
            sum5 <= 18'd0; carry5 <= 18'd0;
        end else begin
            sum5   <= sum4 ^ (carry4 << 1) ^ s6;
            carry5 <= (sum4 & (carry4 << 1)) | (s6 & (carry4 << 1)) | (sum4 & s6);
        end
    end

    // ---------------- FINAL STAGE ----------------//
    reg [17:0] final_sum;
    always @(posedge clk or posedge rst) begin
        if (rst)
            final_sum <= 18'd0;
        else
            final_sum <= sum5 + (carry5 << 1) + s7;
    end

    // ---------------- OUTPUT ----------------//
    reg [17:0] y_reg;
    always @(posedge clk or posedge rst) begin
        if (rst)
            y_reg <= 18'd0;
        else
            y_reg <= final_sum;
    end

    // led is intentionally the lower 16 bits of an 18-bit result.
    // The true FIR output needs 18 bits (max 231030); this truncates
    // the top 2 bits. If you need full precision, widen `led` to
    // [17:0] instead of silently dropping MSBs.
    assign led = y_reg[15:0];

endmodule

csa_da_fir/csa_tb.v
`timescale 1ns/1ps

module csa_tb;

reg clk;
reg rst;
reg [7:0] x;

wire [15:0] led2;

csa_da_openlane u3 (
    .clk(clk),
    .rst(rst),
    .x(x),
    .led(led2)
);

// Clock generation
always #5 clk = ~clk;

// VCD dump
initial begin
    $dumpfile("csa_da_openlane.vcd");
    $dumpvars(0, csa_tb);
end

// Stimulus
initial begin
    clk = 0;
    rst = 1;
    x = 0;

    #20 rst = 0;

    #10 x = 8'd1;
    #10 x = 8'd2;
    #10 x = 8'd3;
    #10 x = 8'd4;
    #10 x = 8'd5;
    #10 x = 8'd6;

    #100 x = 8'd10;

    #10 $finish;
end

endmodule

csa_da_fir/csa_da_openlane.vcd
$date
	Sun Jun 21 22:51:51 2026
$end
$version
	Icarus Verilog
$end
$timescale
	1ps
$end
$scope module csa_tb $end
$var wire 16 ! led2 [15:0] $end
$var reg 1 " clk $end
$var reg 1 # rst $end
$var reg 8 $ x [7:0] $end
$scope module u3 $end
$var wire 1 " clk $end
$var wire 1 # rst $end
$var wire 8 % x [7:0] $end
$var wire 16 & led [15:0] $end
$var wire 17 ' bit_sum0_ext [16:0] $end
$var reg 10 ( bit_sum0 [9:0] $end
$var reg 10 ) bit_sum1 [9:0] $end
$var reg 10 * bit_sum2 [9:0] $end
$var reg 10 + bit_sum3 [9:0] $end
$var reg 10 , bit_sum4 [9:0] $end
$var reg 10 - bit_sum5 [9:0] $end
$var reg 10 . bit_sum6 [9:0] $end
$var reg 10 / bit_sum7 [9:0] $end
$var reg 18 0 carry1 [17:0] $end
$var reg 18 1 carry2 [17:0] $end
$var reg 18 2 carry3 [17:0] $end
$var reg 18 3 carry4 [17:0] $end
$var reg 18 4 carry5 [17:0] $end
$var reg 18 5 final_sum [17:0] $end
$var reg 17 6 s0 [16:0] $end
$var reg 17 7 s1 [16:0] $end
$var reg 17 8 s2 [16:0] $end
$var reg 17 9 s3 [16:0] $end
$var reg 17 : s4 [16:0] $end
$var reg 17 ; s5 [16:0] $end
$var reg 17 < s6 [16:0] $end
$var reg 17 = s7 [16:0] $end
$var reg 8 > sh0 [7:0] $end
$var reg 8 ? sh1 [7:0] $end
$var reg 8 @ sh10 [7:0] $end
$var reg 8 A sh11 [7:0] $end
$var reg 8 B sh12 [7:0] $end
$var reg 8 C sh13 [7:0] $end
$var reg 8 D sh14 [7:0] $end
$var reg 8 E sh15 [7:0] $end
$var reg 8 F sh2 [7:0] $end
$var reg 8 G sh3 [7:0] $end
$var reg 8 H sh4 [7:0] $end
$var reg 8 I sh5 [7:0] $end
$var reg 8 J sh6 [7:0] $end
$var reg 8 K sh7 [7:0] $end
$var reg 8 L sh8 [7:0] $end
$var reg 8 M sh9 [7:0] $end
$var reg 18 N sum1 [17:0] $end
$var reg 18 O sum2 [17:0] $end
$var reg 18 P sum3 [17:0] $end
$var reg 18 Q sum4 [17:0] $end
$var reg 18 R sum5 [17:0] $end
$var reg 18 S y_reg [17:0] $end
$upscope $end
$upscope $end
$enddefinitions $end
#0
$dumpvars
b0 S
b0 R
b0 Q
b0 P
b0 O
b0 N
b0 M
b0 L
b0 K
b0 J
b0 I
b0 H
b0 G
b0 F
b0 E
b0 D
b0 C
b0 B
b0 A
b0 @
b0 ?
b0 >
b0 =
b0 <
b0 ;
b0 :
b0 9
b0 8
b0 7
b0 6
b0 5
b0 4
b0 3
b0 2
b0 1
b0 0
b0 /
b0 .
b0 -
b0 ,
b0 +
b0 *
b0 )
b0 (
b0 '
b0 &
b0 %
b0 $
1#
0"
b0 !
$end
#5000
1"
#10000
0"
#15000
1"
#20000
0"
0#
#25000
1"
#30000
0"
b1 $
b1 %
#35000
b1 >
1"
#40000
0"
b10 $
b10 %
#45000
b10111 '
b10111 (
b1 ?
b10 >
1"
#50000
0"
b11 $
b11 %
#55000
b1 F
b10 ?
b11 >
b10111 )
b111001 '
b111001 (
b10111 6
1"
#60000
0"
b100 $
b100 %
#65000
b10111 N
b101110 7
b111001 6
b1010000 )
b1110010 '
b1110010 (
b1 G
b10 F
b11 ?
b100 >
1"
#70000
0"
b101 $
b101 %
#75000
b1 H
b10 G
b11 F
b100 ?
b101 >
b10111 *
b10010100 )
b1000110 '
b1000110 (
b10100000 7
b1110010 6
b101000 0
b10111 O
1"
#80000
0"
b110 $
b110 %
#85000
b10111 P
b10000 1
b1000111 O
b100000 0
b11010010 N
b1011100 8
b100101000 7
b1000110 6
b1010000 *
b1101000 )
b10111111 '
b10111111 (
b1 I
b10 H
b11 G
b100 F
b101 ?
b110 >
1"
#90000
0"
#95000
b1 J
b10 I
b11 H
b100 G
b101 F
b110 ?
b10101011 *
b1110001 )
b1110011 '
b1110011 (
b101000000 8
b11010000 7
b10111111 6
b1001100 0
b100110010 N
b1000000 1
b10010010 O
b1100111 P
b10111 Q
1"
#100000
0"
#105000
b10111 R
b1100111 Q
b10000000 2
b10010 P
b10000 1
b110101010 O
b11010000 0
b100101111 N
b1010101100 8
b11100010 7
b1110011 6
b10111000 *
b11001010 )
b100001011 '
b100001011 (
b1 K
b10 J
b11 I
b100 H
b101 G
b110 F
1"
#110000
0"
#115000
b1 L
b10 K
b11 J
b100 I
b101 H
b110 G
b100000101 *
b100111011 )
b1011001 '
b1011001 (
b1011100000 8
b110010100 7
b100001011 6
b11100010 0
b1000111101 N
b100100000 1
b10001111 O
b100000 2
b110001010 P
b100010010 Q
b1100111 R
b10111 5
1"
#120000
0"
#125000
b10111 !
b10111 &
b10111 S
b1100111 5
b100010010 R
b111001010 Q
b0 2
b1011001111 P
b100 1
b1111111001 O
b110000000 0
b1001111111 N
b10000010100 8
b1001110110 7
b1011001 6
b100110010 *
b100111010 )
b11101110 '
b11101110 (
b1 M
b10 L
b11 K
b100 J
b101 I
b110 H
1"
#130000
0"
#135000
b1100111 !
b1100111 &
b1 @
b10 M
b11 L
b100 K
b101 J
b110 I
b110010101 *
b101100010 )
b10100100 '
b10100100 (
b10011001000 8
b1001110100 7
b11101110 6
b1010100 0
b11000111011 N
b1000000000 1
b101111111 O
b1000 2
b1111110001 P
b1011001111 Q
b111001010 R
b100010010 5
b1100111 S
1"
#140000
0"
#145000
b100010010 !
b100010010 &
b100010010 S
b111001010 5
b1011001111 R
b10000 3
b1111100001 Q
b0 2
b10101111111 P
b101000 1
b11010010011 O
b11101100 0
b11001010010 N
b11001010100 8
b1011000100 7
b10100100 6
b110110100 *
b111001000 )
b10110010 '
b10110010 (
b1 A
b10 @
b11 M
b100 L
b101 K
b110 J
1"
#150000
0"
#155000
b111001010 !
b111001010 &
b1 B
b10 A
b11 @
b100 M
b101 L
b110 K
b111110010 *
b111111110 )
b10101100 '
b10101100 (
b11011010000 8
b1110010000 7
b10110010 6
b1011000100 0
b10000110100 N
b1010000 1
b11110001010 O
b10000 2
b11011000011 P
b0 3
b10101111111 Q
b100000 4
b1111000001 R
b1011001111 5
b111001010 S
1"
#160000
0"
#165000
b1011001111 !
b1011001111 &
b1011001111 S
b10000000001 5
b0 4
b10101111111 R
b11011100011 Q
b10000000 2
b11100101010 P
b10000000000 1
b110111100 O
b1010010000 0
b10111110010 N
b11111001000 8
b1111111100 7
b10101100 6
b1001001010 *
b111111010 )
b1101100 '
b1101100 (
b1 C
b10 B
b11 A
b100 @
b101 M
b110 L
1"
#170000
0"
#175000
b10000000001 !
b10000000001 &
b1 D
b10 C
b11 B
b100 A
b101 @
b110 M
b1001011011 *
b1001000100 )
b11010111 '
b11010111 (
b100100101000 8
b1111110100 7
b1101100 6
b1111101100 0
b10010011000 N
b10100100000 1
b11010010 O
b0 2
b100110111100 P
b100000000 3
b11000101010 Q
b11011100011 R
b10101111111 5
b10000000001 S
1"
#180000
0"
b1010 $
b1010 %
#185000
b10101111111 !
b10101111111 &
b10101111111 S
b11011100011 5
b1000000000 4
b10000101010 R
b0 3
b100110111100 Q
b1000000 2
b101010010010 P
b10010011000 1
b1101000000 O
b101101100 0
b101010110000 N
b100101101100 8
b10010001000 7
b11010111 6
b1010010000 *
b1010110001 )
b1110000 '
b1110000 (
b1 E
b10 D
b11 C
b100 B
b101 A
b110 @
b1010 >
1"
